messaging/__init__.py
messaging/eftl/__init__.py
messaging/eftl/connection.py
eftl-1.3.1.dist-info/METADATA
eftl-1.3.1.dist-info/WHEEL
eftl-1.3.1.dist-info/top_level.txt
eftl-1.3.1.dist-info/RECORD
