Metadata-Version: 2.1
Name: eftl
Version: 1.3.1
Summary: TIBCO eFTL client for Python
Home-page: https://www.tibco.com
Author: Cloud Software Group, Inc
Author-email: support@tibco.com
License: UNKNOWN
Platform: UNKNOWN
Classifier: Programming Language :: Python :: 3
Classifier: Programming Language :: Python :: 3.7
Requires-Dist: asyncio
Requires-Dist: datetime
Requires-Dist: jsonpickle
Requires-Dist: autobahn
Requires-Dist: pyOpenSSL
Requires-Dist: service-identity
